exception_nexilum/__init__.py
exception_nexilum/nexilum_error.py
nexilum/__init__.py
nexilum/connect_to.py
nexilum/nexilum.py
nexilum-0.0.6.dist-info/licenses/LICENSE
test_nexilum/__init__.py
test_nexilum/test_connect_to.py
test_nexilum/test_nexilum.py
nexilum-0.0.6.dist-info/METADATA
nexilum-0.0.6.dist-info/WHEEL
nexilum-0.0.6.dist-info/top_level.txt
nexilum-0.0.6.dist-info/RECORD
