Metadata-Version: 2.4
Name: Nexilum
Version: 0.0.6
Summary: A Python library for simplifying HTTP integrations with REST APIs, featuring decorators for authentication handling and request management.
Home-page: https://github.com/ConectarWali/Nexilum
Author: Conectar Wali SAS
Author-email: dev@conectarwalisas.com.co
Classifier: Programming Language :: Python :: 3
Classifier: License :: Other/Proprietary License
Classifier: Operating System :: OS Independent
Requires-Python: >=3.9
License-File: LICENSE
Dynamic: author
Dynamic: author-email
Dynamic: classifier
Dynamic: description
Dynamic: description-content-type
Dynamic: home-page
Dynamic: license-file
Dynamic: requires-python
Dynamic: summary
